pymc_core/__init__.py
pymc_core/hardware/__init__.py
pymc_core/hardware/base.py
pymc_core/hardware/gpio_manager.py
pymc_core/hardware/kiss_serial_wrapper.py
pymc_core/hardware/signal_utils.py
pymc_core/hardware/sx1262_wrapper.py
pymc_core/hardware/wsradio.py
pymc_core/hardware/lora/LoRaRF/SX126x.py
pymc_core/hardware/lora/LoRaRF/SX127x.py
pymc_core/hardware/lora/LoRaRF/__init__.py
pymc_core/hardware/lora/LoRaRF/base.py
pymc_core/node/__init__.py
pymc_core/node/dispatcher.py
pymc_core/node/node.py
pymc_core/node/events/__init__.py
pymc_core/node/events/event_service.py
pymc_core/node/events/events.py
pymc_core/node/handlers/__init__.py
pymc_core/node/handlers/ack.py
pymc_core/node/handlers/advert.py
pymc_core/node/handlers/base.py
pymc_core/node/handlers/control.py
pymc_core/node/handlers/group_text.py
pymc_core/node/handlers/login_response.py
pymc_core/node/handlers/login_server.py
pymc_core/node/handlers/path.py
pymc_core/node/handlers/protocol_request.py
pymc_core/node/handlers/protocol_response.py
pymc_core/node/handlers/text.py
pymc_core/node/handlers/trace.py
pymc_core/protocol/__init__.py
pymc_core/protocol/constants.py
pymc_core/protocol/crypto.py
pymc_core/protocol/identity.py
pymc_core/protocol/packet.py
pymc_core/protocol/packet_builder.py
pymc_core/protocol/packet_filter.py
pymc_core/protocol/packet_utils.py
pymc_core/protocol/transport_keys.py
pymc_core/protocol/utils.py
pymc_core-1.0.6.dist-info/licenses/LICENSE
pymc_core-1.0.6.dist-info/METADATA
pymc_core-1.0.6.dist-info/WHEEL
pymc_core-1.0.6.dist-info/top_level.txt
pymc_core-1.0.6.dist-info/RECORD
