Metadata-Version: 2.4
Name: pymc_core
Version: 1.0.6
Summary: A Python MeshCore library with SPI LoRa radio support
Author-email: Lloyd Newton <lloyd@rightup.co.uk>
License: MIT
Project-URL: Homepage, https://github.com/rightup/pyMC_core
Project-URL: Documentation, https://rightup.github.io/rightup/pyMC_core
Project-URL: Repository, https://github.com/rightup/pyMC_core.git
Project-URL: Issues, https://github.com/rightup/pyMC_core/issues
Keywords: mesh,networking,lora,radio,iot,communication
Classifier: Development Status :: 4 - Beta
Classifier: Intended Audience :: Developers
Classifier: License :: OSI Approved :: MIT License
Classifier: Operating System :: OS Independent
Classifier: Programming Language :: Python :: 3
Classifier: Programming Language :: Python :: 3.9
Classifier: Programming Language :: Python :: 3.10
Classifier: Programming Language :: Python :: 3.11
Classifier: Programming Language :: Python :: 3.12
Classifier: Topic :: Communications
Classifier: Topic :: System :: Networking
Requires-Python: >=3.9
License-File: LICENSE
Requires-Dist: pycryptodome>=3.23.0
Requires-Dist: PyNaCl>=1.5.0
Requires-Dist: pyyaml>=6.0.0
Provides-Extra: radio
Requires-Dist: pyserial>=3.5; extra == "radio"
Provides-Extra: hardware
Requires-Dist: python-periphery>=2.4.1; extra == "hardware"
Requires-Dist: spidev>=3.5; extra == "hardware"
Requires-Dist: pyserial>=3.5; extra == "hardware"
Provides-Extra: websocket
Requires-Dist: websockets>=11.0.0; extra == "websocket"
Provides-Extra: dev
Requires-Dist: pytest>=7.0.0; extra == "dev"
Requires-Dist: pytest-cov>=4.0.0; extra == "dev"
Requires-Dist: pytest-asyncio>=0.21.0; extra == "dev"
Requires-Dist: black>=23.0.0; extra == "dev"
Requires-Dist: isort>=5.12.0; extra == "dev"
Requires-Dist: flake8>=6.0.0; extra == "dev"
Requires-Dist: mypy>=1.0.0; extra == "dev"
Requires-Dist: pre-commit>=3.0.0; extra == "dev"
Provides-Extra: docs
Requires-Dist: mkdocs>=1.5.0; extra == "docs"
Requires-Dist: mkdocs-material>=9.0.0; extra == "docs"
Requires-Dist: mkdocs-git-revision-date-localized-plugin>=1.2.0; extra == "docs"
Requires-Dist: mkdocs-git-committers-plugin-2>=1.2.0; extra == "docs"
Provides-Extra: all
Requires-Dist: pymc_core[dev,docs,hardware,websocket]; extra == "all"
Dynamic: license-file
